glass/__init__.py
glass/_array_api_utils.py
glass/_types.py
glass/_version.py
glass/algorithm.py
glass/arraytools.py
glass/cosmology.py
glass/fields.py
glass/galaxies.py
glass/harmonics.py
glass/jax.py
glass/lensing.py
glass/observations.py
glass/points.py
glass/py.typed
glass/shapes.py
glass/shells.py
glass/user.py
glass/ext/__init__.py
glass/grf/__init__.py
glass/grf/_core.py
glass/grf/_solver.py
glass/grf/_transformations.py
glass-2025.3.dist-info/METADATA
glass-2025.3.dist-info/WHEEL
glass-2025.3.dist-info/licenses/LICENSE
glass-2025.3.dist-info/RECORD
