Metadata-Version: 2.4
Name: glass
Version: 2025.3
Summary: Generator for Large Scale Structure
Project-URL: Changelog, https://glass.readthedocs.io/stable/manual/releases.html
Project-URL: Documentation, https://glass.readthedocs.io/stable
Project-URL: Homepage, https://github.com/glass-dev/glass
Project-URL: Issues, https://github.com/glass-dev/glass/issues
Maintainer-email: Nicolas Tessore <n.tessore@ucl.ac.uk>
License-Expression: MIT
License-File: LICENSE
Classifier: Operating System :: OS Independent
Classifier: Programming Language :: Python :: 3
Classifier: Programming Language :: Python :: 3 :: Only
Classifier: Programming Language :: Python :: 3.10
Classifier: Programming Language :: Python :: 3.11
Classifier: Programming Language :: Python :: 3.12
Classifier: Programming Language :: Python :: 3.13
Classifier: Programming Language :: Python :: 3.14
Classifier: Topic :: Scientific/Engineering :: Astronomy
Classifier: Topic :: Scientific/Engineering :: Physics
Classifier: Typing :: Typed
Requires-Python: >=3.10
Requires-Dist: array-api-compat>=1.12.0
Requires-Dist: array-api-extra>=0.9.0
Requires-Dist: healpix>=2022.11.1
Requires-Dist: healpy>=1.15.0
Requires-Dist: transformcl>=2022.8.9
Provides-Extra: examples
Requires-Dist: camb; extra == 'examples'
Requires-Dist: cosmology-api; extra == 'examples'
Requires-Dist: cosmology-compat-camb; extra == 'examples'
Requires-Dist: glass-ext-camb; extra == 'examples'
Requires-Dist: jupyter; extra == 'examples'
Requires-Dist: matplotlib; extra == 'examples'
